LICENSE
MANIFEST.in
README.rst
setup.cfg
setup.py
lsanomaly/__init__.py
lsanomaly.egg-info/PKG-INFO
lsanomaly.egg-info/SOURCES.txt
lsanomaly.egg-info/dependency_links.txt
lsanomaly.egg-info/requires.txt
lsanomaly.egg-info/top_level.txt