Metadata-Version: 1.1
Name: lsanomaly
Version: 0.1.0
Summary: Least squares anomaly detection.
Home-page: https://github.com/lsanomaly/lsanomaly
Author: David Westerhoff
Author-email: dmwesterhoff@gmail.com
License: MIT
Keywords: anomaly outlier novelty detection machine learning scikit-learn sklearn
Platform: UNKNOWN
Classifier: Intended Audience :: Developers
Classifier: License :: OSI Approved :: MIT License
Classifier: Operating System :: OS Independent
Classifier: Programming Language :: Python
Classifier: Programming Language :: Python :: 2
Classifier: Programming Language :: Python :: 2.7
Classifier: Programming Language :: Python :: 3
Classifier: Programming Language :: Python :: 3.3
Classifier: Programming Language :: Python :: 3.4
Classifier: Programming Language :: Python :: 3.5
Classifier: Topic :: Software Development :: Libraries :: Python Modules
